{"alat":"कण्डते;कण्डेते;कण्डन्ते;कण्डसे;कण्डेथे;कण्डध्वे;कण्डे;कण्डावहे;कण्डामहे","alit":"चकण्डे;चकण्डाते;चकण्डिरे;चकण्डिषे;चकण्डाथे;चकण्डिध्वे;चकण्डे;चकण्डिवहे;चकण्डिमहे","alut":"कण्डिता;कण्डितारौ;कण्डितारः;कण्डितासे;कण्डितासाथे;कण्डिताध्वे;कण्डिताहे;कण्डितास्वहे;कण्डितास्महे","alrut":"कण्डिष्यते;कण्डिष्येते;कण्डिष्यन्ते;कण्डिष्यसे;कण्डिष्येथे;कण्डिष्यध्वे;कण्डिष्ये;कण्डिष्यावहे;कण्डिष्यामहे","alot":"कण्डताम्;कण्डेताम्;कण्डन्ताम्;कण्डस्व;कण्डेथाम्;कण्डध्वम्;कण्डै;कण्डावहै;कण्डामहै","alang":"अकण्डत;अकण्डेताम्;अकण्डन्त;अकण्डथाः;अकण्डेथाम्;अकण्डध्वम्;अकण्डे;अकण्डावहि;अकण्डामहि","avidhiling":"कण्डेत;कण्डेयाताम्;कण्डेरन्;कण्डेथाः;कण्डेयाथाम्;कण्डेध्वम्;कण्डेय;कण्डेवहि;कण्डेमहि","aashirling":"कण्डिषीष्ट;कण्डिषीयास्ताम्;कण्डिषीरन्;कण्डिषीष्ठाः;कण्डिषीयास्थाम्;कण्डिषीध्वम्;कण्डिषीय;कण्डिषीवहि;कण्डिषीमहि","alung":"अकण्डिष्ट;अकण्डिषाताम्;अकण्डिषत;अकण्डिष्ठाः;अकण्डिषाथाम्;अकण्डिध्वम्;अकण्डिषि;अकण्डिष्वहि;अकण्डिष्महि","alrung":"अकण्डिष्यत;अकण्डिष्येताम्;अकण्डिष्यन्त;अकण्डिष्यथाः;अकण्डिष्येथाम्;अकण्डिष्यध्वम्;अकण्डिष्ये;अकण्डिष्यावहि;अकण्डिष्यामहि"}