{"alat":"ददते;ददेते;ददन्ते;ददसे;ददेथे;ददध्वे;ददे;ददावहे;ददामहे",
"alit":"दददे;दददाते;दददिरे;दददिषे;दददाथे;दददिध्वे;दददे;दददिवहे;दददिमहे",
"alut":"ददिता;ददितारौ;ददितारः;ददितासे;ददितासाथे;ददिताध्वे;ददिताहे;ददितास्वहे;ददितास्महे",
"alrut":"ददिष्यते;ददिष्येते;ददिष्यन्ते;ददिष्यसे;ददिष्येथे;ददिष्यध्वे;ददिष्ये;ददिष्यावहे;ददिष्यामहे",
"alot":"ददताम्;ददेताम्;ददन्ताम्;ददस्व;ददेथाम्;ददध्वम्;ददै;ददावहै;ददामहै",
"alang":"अददत;अददेताम्;अददन्त;अददथाः;अददेथाम्;अददध्वम्;अददे;अददावहि;अददामहि",
"avidhiling":"ददेत;ददेयाताम्;ददेरन्;ददेथाः;ददेयाथाम्;ददेध्वम्;ददेय;ददेवहि;ददेमहि",
"aashirling":"ददिषीष्ट;ददिषीयास्ताम्;ददिषीरन्;ददिषीष्ठाः;ददिषीयास्थाम्;ददिषीध्वम्;ददिषीय;ददिषीवहि;ददिषीमहि",
"alung":"अददिष्ट;अददिषाताम्;अददिषत;अददिष्ठाः;अददिषाथाम्;अददिध्वम्;अददिषि;अददिष्वहि;अददिष्महि",
"alrung":"अददिष्यत;अददिष्येताम्;अददिष्यन्त;अददिष्यथाः;अददिष्येथाम्;अददिष्यध्वम्;अददिष्ये;अददिष्यावहि;अददिष्यामहि"}