{"plat":"तङ्गति;तङ्गतः;तङ्गन्ति;तङ्गसि;तङ्गथः;तङ्गथ;तङ्गामि;तङ्गावः;तङ्गामः",
"plit":"ततङ्ग;ततङ्गतुः;ततङ्गुः;ततङ्गिथ;ततङ्गथुः;ततङ्ग;ततङ्ग;ततङ्गिव;ततङ्गिम",
"plut":"तङ्गिता;तङ्गितारौ;तङ्गितारः;तङ्गितासि;तङ्गितास्थः;तङ्गितास्थ;तङ्गितास्मि;तङ्गितास्वः;तङ्गितास्मः",
"plrut":"तङ्गिष्यति;तङ्गिष्यतः;तङ्गिष्यन्ति;तङ्गिष्यसि;तङ्गिष्यथः;तङ्गिष्यथ;तङ्गिष्यामि;तङ्गिष्यावः;तङ्गिष्यामः",
"plot":"तङ्गतात्,तङ्गताद्,तङ्गतु;तङ्गताम्;तङ्गन्तु;तङ्ग,तङ्गतात्,तङ्गताद्;तङ्गतम्;तङ्गत;तङ्गानि;तङ्गाव;तङ्गाम",
"plang":"अतङ्गत्,अतङ्गद्;अतङ्गताम्;अतङ्गन्;अतङ्गः;अतङ्गतम्;अतङ्गत;अतङ्गम्;अतङ्गाव;अतङ्गाम",
"pvidhiling":"तङ्गेत्,तङ्गेद्;तङ्गेताम्;तङ्गेयुः;तङ्गेः;तङ्गेतम्;तङ्गेत;तङ्गेयम्;तङ्गेव;तङ्गेम",
"pashirling":"तङ्ग्यात्,तङ्ग्याद्;तङ्ग्यास्ताम्;तङ्ग्यासुः;तङ्ग्याः;तङ्ग्यास्तम्;तङ्ग्यास्त;तङ्ग्यासम्;तङ्ग्यास्व;तङ्ग्यास्म",
"plung":"अतङ्गीत्,अतङ्गीद्;अतङ्गिष्टाम्;अतङ्गिषुः;अतङ्गीः;अतङ्गिष्टम्;अतङ्गिष्ट;अतङ्गिषम्;अतङ्गिष्व;अतङ्गिष्म",
"plrung":"अतङ्गिष्यत्,अतङ्गिष्यद्;अतङ्गिष्यताम्;अतङ्गिष्यन्;अतङ्गिष्यः;अतङ्गिष्यतम्;अतङ्गिष्यत;अतङ्गिष्यम्;अतङ्गिष्याव;अतङ्गिष्याम"}