{"plat":"रुङ्गति;रुङ्गतः;रुङ्गन्ति;रुङ्गसि;रुङ्गथः;रुङ्गथ;रुङ्गामि;रुङ्गावः;रुङ्गामः","plit":"रुरुङ्ग;रुरुङ्गतुः;रुरुङ्गुः;रुरुङ्गिथ;रुरुङ्गथुः;रुरुङ्ग;रुरुङ्ग;रुरुङ्गिव;रुरुङ्गिम","plut":"रुङ्गिता;रुङ्गितारौ;रुङ्गितारः;रुङ्गितासि;रुङ्गितास्थः;रुङ्गितास्थ;रुङ्गितास्मि;रुङ्गितास्वः;रुङ्गितास्मः","plrut":"रुङ्गिष्यति;रुङ्गिष्यतः;रुङ्गिष्यन्ति;रुङ्गिष्यसि;रुङ्गिष्यथः;रुङ्गिष्यथ;रुङ्गिष्यामि;रुङ्गिष्यावः;रुङ्गिष्यामः","plot":"रुङ्गतात्,रुङ्गताद्,रुङ्गतु;रुङ्गताम्;रुङ्गन्तु;रुङ्ग,रुङ्गतात्,रुङ्गताद्;रुङ्गतम्;रुङ्गत;रुङ्गाणि;रुङ्गाव;रुङ्गाम","plang":"अरुङ्गत्,अरुङ्गद्;अरुङ्गताम्;अरुङ्गन्;अरुङ्गः;अरुङ्गतम्;अरुङ्गत;अरुङ्गम्;अरुङ्गाव;अरुङ्गाम","pvidhiling":"रुङ्गेत्,रुङ्गेद्;रुङ्गेताम्;रुङ्गेयुः;रुङ्गेः;रुङ्गेतम्;रुङ्गेत;रुङ्गेयम्;रुङ्गेव;रुङ्गेम","pashirling":"रुङ्ग्यात्,रुङ्ग्याद्;रुङ्ग्यास्ताम्;रुङ्ग्यासुः;रुङ्ग्याः;रुङ्ग्यास्तम्;रुङ्ग्यास्त;रुङ्ग्यासम्;रुङ्ग्यास्व;रुङ्ग्यास्म","plung":"अरुङ्गीत्,अरुङ्गीद्;अरुङ्गिष्टाम्;अरुङ्गिषुः;अरुङ्गीः;अरुङ्गिष्टम्;अरुङ्गिष्ट;अरुङ्गिषम्;अरुङ्गिष्व;अरुङ्गिष्म","plrung":"अरुङ्गिष्यत्,अरुङ्गिष्यद्;अरुङ्गिष्यताम्;अरुङ्गिष्यन्;अरुङ्गिष्यः;अरुङ्गिष्यतम्;अरुङ्गिष्यत;अरुङ्गिष्यम्;अरुङ्गिष्याव;अरुङ्गिष्याम"}