{"plat":"रवीति,रौति;रुतः,रुवीतः;रुवन्ति;रवीषि,रौषि;रुथः,रुवीथः;रुथ,रुवीथ;रवीमि,रौमि;रुवः,रुवीवः;रुमः,रुवीमः",
"plit":"रुराव;रुरुवतुः;रुरुवुः;रुरविथ;रुरुवथुः;रुरुव;रुरव,रुराव;रुरुविव;रुरुविम",
"plut":"रविता;रवितारौ;रवितारः;रवितासि;रवितास्थः;रवितास्थ;रवितास्मि;रवितास्वः;रवितास्मः",
"plrut":"रविष्यति;रविष्यतः;रविष्यन्ति;रविष्यसि;रविष्यथः;रविष्यथ;रविष्यामि;रविष्यावः;रविष्यामः",
"plot":"रवीतु,रुतात्,रुताद्,रुवीतात्,रुवीताद्,रौतु;रुताम्,रुवीताम्;रुवन्तु;रुतात्,रुताद्,रुवीतात्,रुवीताद्,रुवीहि,रुहि;रुतम्,रुवीतम्;रुत,रुवीत;रवाणि;रवाव;रवाम",
"plang":"अरवीत्,अरवीद्,अरौत्,अरौद्;अरुताम्,अरुवीताम्;अरुवन्;अरवीः,अरौः;अरुतम्,अरुवीतम्;अरुत,अरुवीत;अरवम्;अरुव,अरुवीव;अरुम,अरुवीम",
"pvidhiling":"रुयात्,रुयाद्,रुवीयात्,रुवीयाद्;रुयाताम्,रुवीयाताम्;रुयुः,रुवीयुः;रुयाः,रुवीयाः;रुयातम्,रुवीयातम्;रुयात,रुवीयात;रुयाम्,रुवीयाम्;रुयाव,रुवीयाव;रुयाम,रुवीयाम",
"pashirling":"रूयात्,रूयाद्;रूयास्ताम्;रूयासुः;रूयाः;रूयास्तम्;रूयास्त;रूयासम्;रूयास्व;रूयास्म",
"plung":"अरावीत्,अरावीद्;अराविष्टाम्;अराविषुः;अरावीः;अराविष्टम्;अराविष्ट;अराविषम्;अराविष्व;अराविष्म",
"plrung":"अरविष्यत्,अरविष्यद्;अरविष्यताम्;अरविष्यन्;अरविष्यः;अरविष्यतम्;अरविष्यत;अरविष्यम्;अरविष्याव;अरविष्याम"}